{
    "scenario_id": "AS0014",
    "mission_class": "Area Search",
    "scenario_objective": {
        "objective_name": "locate static target",
        "routes_of_interest": [],
        "areas_of_interest": [
            {
                "polygon_vertices": [
                    [
                        [
                            -124.64,
                            -129.73
                        ],
                        [
                            -2.19,
                            -129.73
                        ],
                        [
                            -2.19,
                            -10.61
                        ],
                        [
                            -124.64,
                            -10.61
                        ],
                        [
                            -124.64,
                            -129.73
                        ]
                    ]
                ],
                "no_earlier_than": [],
                "no_later_than": []
            }
        ],
        "entities_of_interest": [
            {
                "entity_id": "Car_139",
                "entity_type": "Car",
                "attributes": {
                    "color": "red",
                    "class": []
                },
                "priority": 1,
                "no_earlier_than": [],
                "no_later_than": [],
                "entity_priors": {
                    "last_known_location": [],
                    "last_known_movement_direction": [],
                    "location_belief_map": [
                        {
                            "polygon_vertices": [
                                [
                                    [
                                        -63.415,
                                        -70.17
                                    ],
                                    [
                                        -63.415,
                                        -129.73
                                    ],
                                    [
                                        -124.64,
                                        -129.73
                                    ],
                                    [
                                        -124.64,
                                        -70.17
                                    ],
                                    [
                                        -63.415,
                                        -70.17
                                    ]
                                ]
                            ],
                            "probability": 0.25
                        },
                        {
                            "polygon_vertices": [
                                [
                                    [
                                        -63.415,
                                        -70.17
                                    ],
                                    [
                                        -2.19,
                                        -70.17
                                    ],
                                    [
                                        -2.19,
                                        -10.61
                                    ],
                                    [
                                        -63.415,
                                        -10.61
                                    ],
                                    [
                                        -63.415,
                                        -70.17
                                    ]
                                ]
                            ],
                            "probability": 0.25
                        },
                        {
                            "polygon_vertices": [
                                [
                                    [
                                        -63.415,
                                        -70.17
                                    ],
                                    [
                                        -2.19,
                                        -70.17
                                    ],
                                    [
                                        -2.19,
                                        -129.73
                                    ],
                                    [
                                        -63.415,
                                        -129.73
                                    ],
                                    [
                                        -63.415,
                                        -70.17
                                    ]
                                ]
                            ],
                            "probability": 0.15
                        },
                        {
                            "polygon_vertices": [
                                [
                                    [
                                        -63.415,
                                        -70.17
                                    ],
                                    [
                                        -63.415,
                                        -10.61
                                    ],
                                    [
                                        -124.64,
                                        -10.61
                                    ],
                                    [
                                        -124.64,
                                        -70.17
                                    ],
                                    [
                                        -63.415,
                                        -70.17
                                    ]
                                ]
                            ],
                            "probability": 0.35
                        }
                    ]
                },
                "entity_trajectory": {
                    "trajectory_file": [],
                    "speed": [],
                    "start_time": []
                }
            }
        ]
    },
    "scenario_constraints": {
        "spatial_constraints": {
            "keep_out_zones": [
                {
                    "keep_out_polygon_vertices": [
                        [
                            -38.0,
                            -75.0
                        ],
                        [
                            47.0,
                            -75.0
                        ],
                        [
                            47.0,
                            -40.0
                        ],
                        [
                            -38.0,
                            -40.0
                        ],
                        [
                            -38.0,
                            -75.0
                        ]
                    ],
                    "no_earlier_than": [
                        []
                    ],
                    "no_later_than": []
                }
            ],
            "stay_within_zones": []
        }
    },
    "scenario_thread": "maneuver_thread",
    "pre_mission_context": [
        {
            "entity_id": "Car_139",
            "related_entity_type": "tree",
            "related_entity_id": [],
            "relationship_context": "spatial",
            "relationship_value": "next_to",
            "related_entity_attribute": {}
        },
        {
            "entity_id": "Car_139",
            "related_entity_type": "road",
            "related_entity_id": [],
            "relationship_context": "spatial",
            "relationship_value": "NOT_on_top_of",
            "related_entity_attribute": {}
        },
        {
            "entity_id": "Car_139",
            "related_entity_type": "road",
            "related_entity_id": [],
            "relationship_context": "spatial",
            "relationship_value": "orthogonal_to",
            "related_entity_attribute": {}
        }
    ]
}